CHANGES.txt
MANIFEST.in
setup.cfg
setup.py
justified/__init__.py
justified/justified.py
justified.egg-info/PKG-INFO
justified.egg-info/SOURCES.txt
justified.egg-info/dependency_links.txt
justified.egg-info/top_level.txt