Metadata-Version: 1.0
Name: justified
Version: 0.1.0
Summary: Python implementation of the Knuth-Plass algorithm for fixed-width type
Home-page: http://github.com/benjamin9999/justified/
Author: Benjamin Yates
Author-email: benjamin@rqdq.com
License: MIT
Platform: UNKNOWN
